CHANGELOG.md
CODE_OF_CONDUCT.md
CONTRIBUTING.md
LICENSE
appstrap/__init__.py
appstrap/core.py
appstrap/exceptions.py
appstrap/utils.py
appstrap-0.1.0.dist-info/entry_points.txt
appstrap-0.1.0.dist-info/LICENSE
appstrap-0.1.0.dist-info/WHEEL
appstrap-0.1.0.dist-info/METADATA
appstrap-0.1.0.dist-info/RECORD
